{
    "dataset": "unfiltered",
    "output_dir": "multitask",
    "word_embed": "bert",
    "encoder": "transformer",
    "pooling": "min",
    "freeze_embedding": false,
    "bidirectional": false,
    "save_best_model": false,
    "class_weight": "balanced",
    "loss": "logloss",
    "label_schema": "111",
    "n_heads": 4,
    "n_layers": 1,
    "n_epochs": 10,
    "scenario_dir": "experiments/multitask/unfiltered/transformer/balanced/logloss/min/1/4/unidirectional/111",
    "best_epoch": 10,
    "train_started_at": "2023-12-07 04:11:23.534599",
    "train_finished_at": "2023-12-07 04:12:56.533801",
    "train_duration": "92.999202 seconds",
    "eval_started_at": "2023-12-07 04:12:56.862948",
    "eval_finished_at": "2023-12-07 04:12:57.469528",
    "eval_duration": "0.60658 seconds"
}