{
    "dataset": "unfiltered",
    "output_dir": "multitask",
    "word_embed": "bert",
    "encoder": "transformer",
    "pooling": "mean",
    "freeze_embedding": false,
    "bidirectional": false,
    "save_best_model": false,
    "class_weight": "balanced",
    "loss": "logloss",
    "label_schema": "111",
    "n_heads": 4,
    "n_layers": 3,
    "n_epochs": 10,
    "scenario_dir": "experiments/multitask/unfiltered/transformer/balanced/logloss/mean/3/4/unidirectional/111",
    "best_epoch": 7,
    "train_started_at": "2023-12-07 04:53:51.709965",
    "train_finished_at": "2023-12-07 04:55:34.996101",
    "train_duration": "103.286136 seconds",
    "eval_started_at": "2023-12-07 04:55:35.413007",
    "eval_finished_at": "2023-12-07 04:55:36.078201",
    "eval_duration": "0.665194 seconds"
}